nfelodcm/__init__.py
nfelodcm/nfelodcm/nfelodcm.py
nfelodcm/nfelodcm/tests.py
nfelodcm/nfelodcm/Engine/DCMTable.py
nfelodcm/nfelodcm/Engine/__init__.py
nfelodcm/nfelodcm/Engine/Assignments/__init__.py
nfelodcm/nfelodcm/Engine/Assignments/assignment.py
nfelodcm/nfelodcm/Engine/Assignments/assignments/__init__.py
nfelodcm/nfelodcm/Engine/Assignments/assignments/desc_based_plays.py
nfelodcm/nfelodcm/Engine/Assignments/assignments/fastr_team_repl.py
nfelodcm/nfelodcm/Engine/Assignments/assignments/format_player_file.py
nfelodcm/nfelodcm/Engine/Assignments/assignments/format_qb_file.py
nfelodcm/nfelodcm/Engine/Assignments/assignments/penalty_formatting.py
nfelodcm/nfelodcm/Engine/Assignments/assignments/player_stats_repl.py
nfelodcm/nfelodcm/Engine/Assignments/assignments/score_clean.py
nfelodcm/nfelodcm/Engine/Assignments/assignments/temp_players_handle.py
nfelodcm/nfelodcm/Engine/Primatives/DataPull.py
nfelodcm/nfelodcm/Engine/Primatives/Freshness.py
nfelodcm/nfelodcm/Engine/Primatives/LocalIO.py
nfelodcm/nfelodcm/Engine/Primatives/TableMap.py
nfelodcm/nfelodcm/Engine/Primatives/__init__.py
nfelodcm/nfelodcm/Maps/coaches.json
nfelodcm/nfelodcm/Maps/filmmargins.json
nfelodcm/nfelodcm/Maps/games.json
nfelodcm/nfelodcm/Maps/hfa.json
nfelodcm/nfelodcm/Maps/logos.json
nfelodcm/nfelodcm/Maps/market_data.json
nfelodcm/nfelodcm/Maps/nfelo_games.json
nfelodcm/nfelodcm/Maps/participants.json
nfelodcm/nfelodcm/Maps/pbp.json
nfelodcm/nfelodcm/Maps/player_stats.json
nfelodcm/nfelodcm/Maps/player_stats_season.json
nfelodcm/nfelodcm/Maps/players.json
nfelodcm/nfelodcm/Maps/qb_meta.json
nfelodcm/nfelodcm/Maps/qbelo.json
nfelodcm/nfelodcm/Maps/qbr.json
nfelodcm/nfelodcm/Maps/rosters.json
nfelodcm/nfelodcm/Maps/srs_ratings.json
nfelodcm/nfelodcm/Maps/stadiums.json
nfelodcm/nfelodcm/Maps/stadiums_rolling_stats.json
nfelodcm/nfelodcm/Maps/team_stadiums.json
nfelodcm/nfelodcm/Maps/team_stadiums_rolling_stats.json
nfelodcm/nfelodcm/Maps/wepa.json
nfelodcm/nfelodcm/Maps/wt_ratings.json
nfelodcm-0.1.24.dist-info/METADATA
nfelodcm-0.1.24.dist-info/WHEEL
nfelodcm-0.1.24.dist-info/top_level.txt
nfelodcm-0.1.24.dist-info/RECORD
