Metadata-Version: 2.4
Name: nfelodcm
Version: 0.1.24
Summary: Python package for loading and caching CSVs hosted on github into pandas dataframes
Author-email: Robert Greer <nfl@robbygreer.com>
Maintainer-email: Robert Greer <nfl@robbygreer.com>
License: MIT
Project-URL: homepage, https://github.com/greerreNFL/nfelodcm
Project-URL: repository, https://github.com/greerreNFL/nfelodcm.git
Keywords: nfl,nflfastR,nfelo
Classifier: Programming Language :: Python
Classifier: Programming Language :: Python :: 3
Classifier: Programming Language :: Python :: 3.10
Requires-Python: >=3.11
Requires-Dist: setuptools>=67.6.0
Requires-Dist: wheel
Requires-Dist: pandas>=1.5.3
Requires-Dist: requests
